richillcapital_core-1.3.0.dist-info/METADATA
richillcapital_core-1.3.0.dist-info/WHEEL
richillcapital_core/__init__.py
richillcapital_core/abstractions/__init__.py
richillcapital_core/abstractions/entity.py
richillcapital_core/abstractions/enumeration.py
richillcapital_core/abstractions/value_object.py
richillcapital_core/entities/__init__.py
richillcapital_core/entities/user.py
richillcapital_core/entities/work.py
richillcapital_core/enumerations/__init__.py
richillcapital_core/enumerations/trading_platform.py
richillcapital_core/enumerations/work_status.py
richillcapital_core/value_objects/__init__.py
richillcapital_core/value_objects/email.py
richillcapital_core/value_objects/user_id.py
richillcapital_core/value_objects/work_id.py
richillcapital_core-1.3.0.dist-info/RECORD
