Metadata-Version: 2.1
Name: richillcapital-core
Version: 1.3.0
Summary: A python package that provides core domain objects.
Author-Email: Mengsyue Amao Tsai <mengsyue.tsai@outlook.com>
License: MIT
Requires-Python: >=3.11
